<?xml version="1.0" encoding="utf-8"?>
<Vocabulary xmlns:xsi="http://www.w3.org/2001/XMLSchema-instance" xsi:noNamespaceSchemaLocation="http://vocabsservices.getty.edu/Schemas/AAT/AATGetSubject.xsd">
  <Subject Subject_ID="300020143">
    <Parent_Relationships>
      <Preferred_Parent>
        <Parent_Subject_ID>300106921</Parent_Subject_ID>
        <Relationship_Type>Parent/Child</Relationship_Type>
        <Historic_Flag>Current</Historic_Flag>
        <Parent_String>Aegean styles [300106921], Aegean [300020059], Mediterranean (Early Western World) [300020058], Early Western World [300019255], styles, periods, and cultures by region [300111079], Styles and Periods (hierarchy name) [300015646], Styles and Periods Facet [300264088]</Parent_String>
        <Hier_Rel_Type>Genus/Species-BTG</Hier_Rel_Type>
      </Preferred_Parent>
    </Parent_Relationships>
    <Descriptive_Notes>
      <Descriptive_Note>
        <Note_Text>The culture and styles of the Aegean island of Crete especially during the Minoan period between circa 3500 and 1050 BCE when Crete flourished as the political, economic, and cultural center of the Aegean. Significant artistic production includes fanciful and decorative pottery, small-scale sculptures such as the snake goddess figurines, and the construction and decoration of royal palaces.</Note_Text>
        <Note_Language>English</Note_Language>
        <Note_Contributors>
          <Note_Contributor>
            <Contributor_id>10000000/VP</Contributor_id>
          </Note_Contributor>
        </Note_Contributors>
        <Note_Sources>
          <Note_Source>
            <Source>
              <Source_ID>2000079228/Grove Art Online (2008-)</Source_ID>
            </Source>
          </Note_Source>
        </Note_Sources>
      </Descriptive_Note>
      <Descriptive_Note>
        <Note_Text>Se refiere al estilo de producción artística en la isla de Creta en el Mar Egeo sobre todo durante el período Minoico entre alrededor del 3500 a.C y el 1050 a.C aproximadamente cuando Creta floreció como el centro político, económico y cultural del Mar Egeo. La producción artística relevante incluye alfarería imaginativa y decorativa, esculturas en pequeña escala como las estatuillas de la diosa serpiente y la construcción y decoración de palacios reales.</Note_Text>
        <Note_Language>Spanish</Note_Language>
        <Note_Contributors>
          <Note_Contributor>
            <Contributor_id>10000131/CDBP-SNPC</Contributor_id>
          </Note_Contributor>
        </Note_Contributors>
        <Note_Sources>
          <Note_Source>
            <Source>
              <Source_ID>2000051034/TAA database (2000-)</Source_ID>
            </Source>
          </Note_Source>
        </Note_Sources>
      </Descriptive_Note>
      <Descriptive_Note>
        <Note_Text>Verwijst naar de stijl van kunstvoorwerpen zoals voortgebracht op het Egeïsche eiland Kreta, in het bijzonder tijdens de Minoïsche periode van circa 3500 tot 1050 v. Chr., toen Kreta een bloeiperiode kende als politiek, economisch en cultureel centrum van de Egeïsche wereld. De belangrijke kunstvoorwerpen waren fantasierijk en decoratief aardewerk, kleine beeldhouwwerken, zoals slangengodinnen, en de bouw en decoratie van koninklijke paleizen.</Note_Text>
        <Note_Language>Dutch</Note_Language>
        <Note_Contributors>
          <Note_Contributor>
            <Contributor_id>10000205/AAT-Ned</Contributor_id>
          </Note_Contributor>
        </Note_Contributors>
        <Note_Sources>
          <Note_Source>
            <Source>
              <Source_ID>2000113770/AAT-Ned (1994-)</Source_ID>
            </Source>
          </Note_Source>
          <Note_Source>
            <Source>
              <Source_ID>2000052381/Van Dale Engels-Nederlands (1989)</Source_ID>
            </Source>
          </Note_Source>
        </Note_Sources>
      </Descriptive_Note>
      <Descriptive_Note>
        <Note_Text>指稱於愛琴海的克里特(Crete)島上發展之藝術創作風格，特指克里特島於西元前3500年至西元前1050年的邁諾安文化時期當中，作為愛琴海政治、經濟與文化中心所發展出的風格。此時重要的藝術創作包含了花俏且裝飾豐富的陶器、例如女蛇神小塑像等，以及皇室宮殿的建造與裝飾。</Note_Text>
        <Note_Language>Chinese (traditional)</Note_Language>
        <Note_Contributors>
          <Note_Contributor>
            <Contributor_id>10000250/AS-Academia Sinica</Contributor_id>
          </Note_Contributor>
        </Note_Contributors>
      </Descriptive_Note>
      <Descriptive_Note>
        <Note_Text>A cultura e os estilos da ilha egeia de Creta, especialmente durante o período minóico entre cerca de 3500 e 1050 aC, quando Creta floresceu como o centro político, econômico e cultural do mar Egeu. A produção artística significativa inclui cerâmica fantasiosa e decorativa, esculturas em pequena escala, como as estatuetas da deusa cobra, e a construção e decoração de palácios reais.</Note_Text>
        <Note_Language>Portuguese</Note_Language>
        <Note_Contributors>
          <Note_Contributor>
            <Contributor_id>10000316/CVAA-BR</Contributor_id>
          </Note_Contributor>
        </Note_Contributors>
        <Note_Sources>
          <Note_Source>
            <Source>
              <Source_ID>2000109633/CVAA-BR Consortium (2020-)</Source_ID>
            </Source>
          </Note_Source>
        </Note_Sources>
      </Descriptive_Note>
    </Descriptive_Notes>
    <Record_Type>Concept</Record_Type>
    <Merged_Status>Merged</Merged_Status>
    <Sort_Order>5</Sort_Order>
    <Terms>
      <Preferred_Term>
        <Term_Text>Cretan</Term_Text>
        <Display_Name>N/A</Display_Name>
        <Historic_Flag>Current</Historic_Flag>
        <Vernacular>Undetermined</Vernacular>
        <Term_ID>1000020143</Term_ID>
        <Term_Languages>
          <Term_Language>
            <Language>70051/English</Language>
            <Preferred>Preferred</Preferred>
            <Qualifier>
            </Qualifier>
            <Term_Type>Descriptor</Term_Type>
            <Part_of_Speech>Adjectival</Part_of_Speech>
            <Lang_Stat>Undetermined</Lang_Stat>
          </Term_Language>
        </Term_Languages>
        <Term_Contributors>
          <Term_Contributor>
            <Contributor_id>10000000/VP</Contributor_id>
            <Preferred>Preferred</Preferred>
          </Term_Contributor>
          <Term_Contributor>
            <Contributor_id>10000088/GCI</Contributor_id>
            <Preferred>Preferred</Preferred>
          </Term_Contributor>
        </Term_Contributors>
        <Term_Sources>
          <Term_Source>
            <Source>
              <Source_ID>2000015851/Spitens, Greek and Etruscan Painting (1965)</Source_ID>
            </Source>
            <Page>12</Page>
            <Preferred>Preferred</Preferred>
          </Term_Source>
          <Term_Source>
            <Source>
              <Source_ID>2000041511/Vermeule, Greece in the Bronze Age (1964)</Source_ID>
            </Source>
            <Page>165</Page>
            <Preferred>Preferred</Preferred>
          </Term_Source>
          <Term_Source>
            <Source>
              <Source_ID>2000051089/AATA database (2002-) </Source_ID>
            </Source>
            <Page>122456 checked 26 January 2012</Page>
            <Preferred>Preferred</Preferred>
          </Term_Source>
          <Term_Source>
            <Source>
              <Source_ID>2000079228/Grove Art Online (2008-)</Source_ID>
            </Source>
            <Page>
            </Page>
            <Preferred>Non Preferred</Preferred>
          </Term_Source>
        </Term_Sources>
      </Preferred_Term>
      <Non-Preferred_Term>
        <Term_Text>Cretense</Term_Text>
        <Display_Name>N/A</Display_Name>
        <Historic_Flag>Current</Historic_Flag>
        <Vernacular>Undetermined</Vernacular>
        <Term_ID>1000422296</Term_ID>
        <Term_Languages>
          <Term_Language>
            <Language>70641/Spanish</Language>
            <Preferred>Preferred</Preferred>
            <Qualifier>
            </Qualifier>
            <Term_Type>Descriptor</Term_Type>
            <Part_of_Speech>Undetermined</Part_of_Speech>
            <Lang_Stat>Undetermined</Lang_Stat>
          </Term_Language>
          <Term_Language>
            <Language>70543/Portuguese</Language>
            <Preferred>Non Preferred</Preferred>
            <Qualifier>
            </Qualifier>
            <Term_Type>Alternate Descriptor</Term_Type>
            <Part_of_Speech>Singular Noun</Part_of_Speech>
            <Lang_Stat>Undetermined</Lang_Stat>
          </Term_Language>
        </Term_Languages>
        <Term_Contributors>
          <Term_Contributor>
            <Contributor_id>10000131/CDBP-SNPC</Contributor_id>
            <Preferred>Preferred</Preferred>
          </Term_Contributor>
          <Term_Contributor>
            <Contributor_id>10000316/CVAA-BR</Contributor_id>
            <Preferred>Non Preferred</Preferred>
          </Term_Contributor>
        </Term_Contributors>
        <Term_Sources>
          <Term_Source>
            <Source>
              <Source_ID>2000048810/Moliner, Diccionario de uso del español (2004)</Source_ID>
            </Source>
            <Page>I:802</Page>
            <Preferred>Preferred</Preferred>
          </Term_Source>
          <Term_Source>
            <Source>
              <Source_ID>2000109633/CVAA-BR Consortium (2020-)</Source_ID>
            </Source>
            <Page>
            </Page>
            <Preferred>Non Preferred</Preferred>
          </Term_Source>
        </Term_Sources>
      </Non-Preferred_Term>
      <Non-Preferred_Term>
        <Term_Text>Kretenzisch</Term_Text>
        <Display_Name>N/A</Display_Name>
        <Historic_Flag>Current</Historic_Flag>
        <Vernacular>Undetermined</Vernacular>
        <Term_ID>1000474515</Term_ID>
        <Term_Languages>
          <Term_Language>
            <Language>70261/Dutch</Language>
            <Preferred>Preferred</Preferred>
            <Qualifier>
            </Qualifier>
            <Term_Type>Descriptor</Term_Type>
            <Part_of_Speech>Undetermined</Part_of_Speech>
            <Lang_Stat>Undetermined</Lang_Stat>
          </Term_Language>
        </Term_Languages>
        <Term_Contributors>
          <Term_Contributor>
            <Contributor_id>10000205/AAT-Ned</Contributor_id>
            <Preferred>Preferred</Preferred>
          </Term_Contributor>
        </Term_Contributors>
        <Term_Sources>
          <Term_Source>
            <Source>
              <Source_ID>2000113770/AAT-Ned (1994-)</Source_ID>
            </Source>
            <Page>
            </Page>
            <Preferred>Preferred</Preferred>
          </Term_Source>
          <Term_Source>
            <Source>
              <Source_ID>2000052381/Van Dale Engels-Nederlands (1989)</Source_ID>
            </Source>
            <Page>
            </Page>
            <Preferred>Unknown</Preferred>
          </Term_Source>
        </Term_Sources>
      </Non-Preferred_Term>
      <Non-Preferred_Term>
        <Term_Text>克利特島的</Term_Text>
        <Display_Name>N/A</Display_Name>
        <Historic_Flag>Current</Historic_Flag>
        <Vernacular>Undetermined</Vernacular>
        <Term_ID>1000760055</Term_ID>
        <Term_Languages>
          <Term_Language>
            <Language>72551/Chinese (traditional)</Language>
            <Preferred>Preferred</Preferred>
            <Qualifier>
            </Qualifier>
            <Term_Type>Descriptor</Term_Type>
            <Part_of_Speech>Undetermined</Part_of_Speech>
            <Lang_Stat>Undetermined</Lang_Stat>
          </Term_Language>
        </Term_Languages>
        <Term_Contributors>
          <Term_Contributor>
            <Contributor_id>10000250/AS-Academia Sinica</Contributor_id>
            <Preferred>Preferred</Preferred>
          </Term_Contributor>
        </Term_Contributors>
        <Term_Sources>
          <Term_Source>
            <Source>
              <Source_ID>2000079740/AS-Academia Sinica data (2014-)</Source_ID>
            </Source>
            <Page>
            </Page>
            <Preferred>Preferred</Preferred>
          </Term_Source>
        </Term_Sources>
      </Non-Preferred_Term>
      <Non-Preferred_Term>
        <Term_Text>ke li te dao de</Term_Text>
        <Display_Name>N/A</Display_Name>
        <Historic_Flag>Current</Historic_Flag>
        <Vernacular>Undetermined</Vernacular>
        <Term_ID>1000760060</Term_ID>
        <Term_Languages>
          <Term_Language>
            <Language>72586/Chinese (transliterated Pinyin without tones)</Language>
            <Preferred>Preferred</Preferred>
            <Qualifier>
            </Qualifier>
            <Term_Type>Used For Term</Term_Type>
            <Part_of_Speech>Undetermined</Part_of_Speech>
            <Lang_Stat>Undetermined</Lang_Stat>
          </Term_Language>
        </Term_Languages>
        <Term_Contributors>
          <Term_Contributor>
            <Contributor_id>10000250/AS-Academia Sinica</Contributor_id>
            <Preferred>Non Preferred</Preferred>
          </Term_Contributor>
        </Term_Contributors>
        <Term_Sources>
          <Term_Source>
            <Source>
              <Source_ID>2000079740/AS-Academia Sinica data (2014-)</Source_ID>
            </Source>
            <Page>
            </Page>
            <Preferred>Non Preferred</Preferred>
          </Term_Source>
        </Term_Sources>
      </Non-Preferred_Term>
      <Non-Preferred_Term>
        <Term_Text>kè lì tè dǎo de</Term_Text>
        <Display_Name>N/A</Display_Name>
        <Historic_Flag>Current</Historic_Flag>
        <Vernacular>Undetermined</Vernacular>
        <Term_ID>1000760061</Term_ID>
        <Term_Languages>
          <Term_Language>
            <Language>72584/Chinese (transliterated Hanyu Pinyin)</Language>
            <Preferred>Preferred</Preferred>
            <Qualifier>
            </Qualifier>
            <Term_Type>Used For Term</Term_Type>
            <Part_of_Speech>Undetermined</Part_of_Speech>
            <Lang_Stat>Undetermined</Lang_Stat>
          </Term_Language>
        </Term_Languages>
        <Term_Contributors>
          <Term_Contributor>
            <Contributor_id>10000250/AS-Academia Sinica</Contributor_id>
            <Preferred>Non Preferred</Preferred>
          </Term_Contributor>
        </Term_Contributors>
        <Term_Sources>
          <Term_Source>
            <Source>
              <Source_ID>2000079740/AS-Academia Sinica data (2014-)</Source_ID>
            </Source>
            <Page>
            </Page>
            <Preferred>Non Preferred</Preferred>
          </Term_Source>
        </Term_Sources>
      </Non-Preferred_Term>
      <Non-Preferred_Term>
        <Term_Text>k'o li t'e tao te</Term_Text>
        <Display_Name>N/A</Display_Name>
        <Historic_Flag>Current</Historic_Flag>
        <Vernacular>Undetermined</Vernacular>
        <Term_ID>1000760062</Term_ID>
        <Term_Languages>
          <Term_Language>
            <Language>72582/Chinese (transliterated Wade-Giles)</Language>
            <Preferred>Preferred</Preferred>
            <Qualifier>
            </Qualifier>
            <Term_Type>Used For Term</Term_Type>
            <Part_of_Speech>Undetermined</Part_of_Speech>
            <Lang_Stat>Undetermined</Lang_Stat>
          </Term_Language>
        </Term_Languages>
        <Term_Contributors>
          <Term_Contributor>
            <Contributor_id>10000250/AS-Academia Sinica</Contributor_id>
            <Preferred>Non Preferred</Preferred>
          </Term_Contributor>
        </Term_Contributors>
        <Term_Sources>
          <Term_Source>
            <Source>
              <Source_ID>2000079740/AS-Academia Sinica data (2014-)</Source_ID>
            </Source>
            <Page>
            </Page>
            <Preferred>Non Preferred</Preferred>
          </Term_Source>
        </Term_Sources>
      </Non-Preferred_Term>
      <Non-Preferred_Term>
        <Term_Text>克里特島的</Term_Text>
        <Display_Name>N/A</Display_Name>
        <Historic_Flag>Current</Historic_Flag>
        <Vernacular>Undetermined</Vernacular>
        <Term_ID>1000760056</Term_ID>
        <Term_Languages>
          <Term_Language>
            <Language>72551/Chinese (traditional)</Language>
            <Preferred>Non Preferred</Preferred>
            <Qualifier>
            </Qualifier>
            <Term_Type>Used For Term</Term_Type>
            <Part_of_Speech>Undetermined</Part_of_Speech>
            <Lang_Stat>Undetermined</Lang_Stat>
          </Term_Language>
        </Term_Languages>
        <Term_Contributors>
          <Term_Contributor>
            <Contributor_id>10000250/AS-Academia Sinica</Contributor_id>
            <Preferred>Non Preferred</Preferred>
          </Term_Contributor>
        </Term_Contributors>
        <Term_Sources>
          <Term_Source>
            <Source>
              <Source_ID>2000079740/AS-Academia Sinica data (2014-)</Source_ID>
            </Source>
            <Page>
            </Page>
            <Preferred>Non Preferred</Preferred>
          </Term_Source>
        </Term_Sources>
      </Non-Preferred_Term>
      <Non-Preferred_Term>
        <Term_Text>克里特風格</Term_Text>
        <Display_Name>N/A</Display_Name>
        <Historic_Flag>Current</Historic_Flag>
        <Vernacular>Undetermined</Vernacular>
        <Term_ID>1000760057</Term_ID>
        <Term_Languages>
          <Term_Language>
            <Language>72551/Chinese (traditional)</Language>
            <Preferred>Non Preferred</Preferred>
            <Qualifier>
            </Qualifier>
            <Term_Type>Used For Term</Term_Type>
            <Part_of_Speech>Undetermined</Part_of_Speech>
            <Lang_Stat>Undetermined</Lang_Stat>
          </Term_Language>
        </Term_Languages>
        <Term_Contributors>
          <Term_Contributor>
            <Contributor_id>10000250/AS-Academia Sinica</Contributor_id>
            <Preferred>Non Preferred</Preferred>
          </Term_Contributor>
        </Term_Contributors>
        <Term_Sources>
          <Term_Source>
            <Source>
              <Source_ID>2000079740/AS-Academia Sinica data (2014-)</Source_ID>
            </Source>
            <Page>
            </Page>
            <Preferred>Non Preferred</Preferred>
          </Term_Source>
        </Term_Sources>
      </Non-Preferred_Term>
      <Non-Preferred_Term>
        <Term_Text>克里特式</Term_Text>
        <Display_Name>N/A</Display_Name>
        <Historic_Flag>Current</Historic_Flag>
        <Vernacular>Undetermined</Vernacular>
        <Term_ID>1000760058</Term_ID>
        <Term_Languages>
          <Term_Language>
            <Language>72551/Chinese (traditional)</Language>
            <Preferred>Non Preferred</Preferred>
            <Qualifier>
            </Qualifier>
            <Term_Type>Used For Term</Term_Type>
            <Part_of_Speech>Undetermined</Part_of_Speech>
            <Lang_Stat>Undetermined</Lang_Stat>
          </Term_Language>
        </Term_Languages>
        <Term_Contributors>
          <Term_Contributor>
            <Contributor_id>10000250/AS-Academia Sinica</Contributor_id>
            <Preferred>Non Preferred</Preferred>
          </Term_Contributor>
        </Term_Contributors>
        <Term_Sources>
          <Term_Source>
            <Source>
              <Source_ID>2000079740/AS-Academia Sinica data (2014-)</Source_ID>
            </Source>
            <Page>
            </Page>
            <Preferred>Non Preferred</Preferred>
          </Term_Source>
        </Term_Sources>
      </Non-Preferred_Term>
      <Non-Preferred_Term>
        <Term_Text>克里特的</Term_Text>
        <Display_Name>N/A</Display_Name>
        <Historic_Flag>Current</Historic_Flag>
        <Vernacular>Undetermined</Vernacular>
        <Term_ID>1000760059</Term_ID>
        <Term_Languages>
          <Term_Language>
            <Language>72551/Chinese (traditional)</Language>
            <Preferred>Non Preferred</Preferred>
            <Qualifier>
            </Qualifier>
            <Term_Type>Used For Term</Term_Type>
            <Part_of_Speech>Undetermined</Part_of_Speech>
            <Lang_Stat>Undetermined</Lang_Stat>
          </Term_Language>
        </Term_Languages>
        <Term_Contributors>
          <Term_Contributor>
            <Contributor_id>10000250/AS-Academia Sinica</Contributor_id>
            <Preferred>Non Preferred</Preferred>
          </Term_Contributor>
        </Term_Contributors>
        <Term_Sources>
          <Term_Source>
            <Source>
              <Source_ID>2000079740/AS-Academia Sinica data (2014-)</Source_ID>
            </Source>
            <Page>
            </Page>
            <Preferred>Non Preferred</Preferred>
          </Term_Source>
        </Term_Sources>
      </Non-Preferred_Term>
      <Non-Preferred_Term>
        <Term_Text>arte cretense</Term_Text>
        <Display_Name>N/A</Display_Name>
        <Historic_Flag>Current</Historic_Flag>
        <Vernacular>Undetermined</Vernacular>
        <Term_ID>1000901481</Term_ID>
        <Term_Languages>
          <Term_Language>
            <Language>70543/Portuguese</Language>
            <Preferred>Preferred</Preferred>
            <Qualifier>
            </Qualifier>
            <Term_Type>Descriptor</Term_Type>
            <Part_of_Speech>Singular Noun</Part_of_Speech>
            <Lang_Stat>Undetermined</Lang_Stat>
          </Term_Language>
        </Term_Languages>
        <Term_Contributors>
          <Term_Contributor>
            <Contributor_id>10000316/CVAA-BR</Contributor_id>
            <Preferred>Preferred</Preferred>
          </Term_Contributor>
        </Term_Contributors>
        <Term_Sources>
          <Term_Source>
            <Source>
              <Source_ID>2000109633/CVAA-BR Consortium (2020-)</Source_ID>
            </Source>
            <Page>
            </Page>
            <Preferred>Preferred</Preferred>
          </Term_Source>
        </Term_Sources>
      </Non-Preferred_Term>
    </Terms>
    <Subject_Contributors>
      <Subject_Contributor>
        <Contributor_id>10000000/VP</Contributor_id>
      </Subject_Contributor>
      <Subject_Contributor>
        <Contributor_id>10000088/GCI</Contributor_id>
      </Subject_Contributor>
      <Subject_Contributor>
        <Contributor_id>10000131/CDBP-SNPC</Contributor_id>
      </Subject_Contributor>
      <Subject_Contributor>
        <Contributor_id>10000205/AAT-Ned</Contributor_id>
      </Subject_Contributor>
      <Subject_Contributor>
        <Contributor_id>10000250/AS-Academia Sinica</Contributor_id>
      </Subject_Contributor>
      <Subject_Contributor>
        <Contributor_id>10000316/CVAA-BR</Contributor_id>
      </Subject_Contributor>
    </Subject_Contributors>
    <Subject_Sources>
      <Subject_Source>
        <Source>
          <Source_ID>2000051089/AATA database (2002-) </Source_ID>
        </Source>
      </Subject_Source>
      <Subject_Source>
        <Source>
          <Source_ID>2000016031/Gardner's Art Through the Ages (1986)</Source_ID>
        </Source>
      </Subject_Source>
      <Subject_Source>
        <Source>
          <Source_ID>2000046672/Grove Dictionary of Art (1996)</Source_ID>
        </Source>
      </Subject_Source>
      <Subject_Source>
        <Source>
          <Source_ID>2000024811/CDMARC Subjects: LCSH (1988-)</Source_ID>
        </Source>
      </Subject_Source>
      <Subject_Source>
        <Source>
          <Source_ID>2000052381/Van Dale Engels-Nederlands (1989)</Source_ID>
        </Source>
      </Subject_Source>
      <Subject_Source>
        <Source>
          <Source_ID>2000109633/CVAA-BR Consortium (2020-)</Source_ID>
        </Source>
      </Subject_Source>
    </Subject_Sources>
  </Subject>
</Vocabulary>