<?xml version="1.0" encoding="utf-8"?>
<Vocabulary xmlns:xsi="http://www.w3.org/2001/XMLSchema-instance" xsi:noNamespaceSchemaLocation="http://vocabsservices.getty.edu/Schemas/AAT/AATGetSubject.xsd">
  <Subject Subject_ID="300006278">
    <Parent_Relationships>
      <Preferred_Parent>
        <Parent_Subject_ID>300164121</Parent_Subject_ID>
        <Relationship_Type>Parent/Child</Relationship_Type>
        <Historic_Flag>Current</Historic_Flag>
        <Parent_String>processing plants [300164121], factories by function [300006238], factories (structures) [300006232], industrial buildings [300006231], industrial structures [300121918], single built works by function [300004894], single built works by specific type [300004795], single built works (built environment) [300004790], Single Built Works (hierarchy name) [300004789], Built Environment (hierarchy name) [300264550], Objects Facet [300264092]</Parent_String>
        <Hier_Rel_Type>Genus/Species-BTG</Hier_Rel_Type>
      </Preferred_Parent>
    </Parent_Relationships>
    <Descriptive_Notes>
      <Descriptive_Note>
        <Note_Text>Factories where bricks are made.</Note_Text>
        <Note_Language>English</Note_Language>
        <Note_Contributors>
          <Note_Contributor>
            <Contributor_id>10000000/VP</Contributor_id>
          </Note_Contributor>
        </Note_Contributors>
        <Note_Sources>
          <Note_Source>
            <Source>
              <Source_ID>2000099620/Legacy AAT data</Source_ID>
            </Source>
          </Note_Source>
        </Note_Sources>
      </Descriptive_Note>
      <Descriptive_Note>
        <Note_Text>Fábrica en la que se fabrican ladrillos.</Note_Text>
        <Note_Language>Spanish</Note_Language>
        <Note_Contributors>
          <Note_Contributor>
            <Contributor_id>10000131/CDBP-SNPC</Contributor_id>
          </Note_Contributor>
        </Note_Contributors>
        <Note_Sources>
          <Note_Source>
            <Source>
              <Source_ID>2000051034/TAA database (2000-)</Source_ID>
            </Source>
          </Note_Source>
        </Note_Sources>
      </Descriptive_Note>
      <Descriptive_Note>
        <Note_Text>Fabrieken waar bakstenen worden gemaakt.</Note_Text>
        <Note_Language>Dutch</Note_Language>
        <Note_Contributors>
          <Note_Contributor>
            <Contributor_id>10000205/AAT-Ned</Contributor_id>
          </Note_Contributor>
        </Note_Contributors>
        <Note_Sources>
          <Note_Source>
            <Source>
              <Source_ID>2000113770/AAT-Ned (1994-)</Source_ID>
            </Source>
          </Note_Source>
          <Note_Source>
            <Source>
              <Source_ID>2000052374/Polytechnisch woordenboek En-Ne (1991)</Source_ID>
            </Source>
          </Note_Source>
        </Note_Sources>
      </Descriptive_Note>
      <Descriptive_Note>
        <Note_Text>Farbrik, in der Ziegel hergestellt werden.</Note_Text>
        <Note_Language>German</Note_Language>
        <Note_Contributors>
          <Note_Contributor>
            <Contributor_id>10000232/IfM-SMB-PK</Contributor_id>
          </Note_Contributor>
        </Note_Contributors>
        <Note_Sources>
          <Note_Source>
            <Source>
              <Source_ID>2000122134/IfM Berlin</Source_ID>
            </Source>
          </Note_Source>
        </Note_Sources>
      </Descriptive_Note>
      <Descriptive_Note>
        <Note_Text>Fábricas onde os tijolos são feitos.</Note_Text>
        <Note_Language>Portuguese</Note_Language>
        <Note_Contributors>
          <Note_Contributor>
            <Contributor_id>10000000/VP</Contributor_id>
          </Note_Contributor>
          <Note_Contributor>
            <Contributor_id>10000179/VP-intern</Contributor_id>
          </Note_Contributor>
        </Note_Contributors>
        <Note_Sources>
          <Note_Source>
            <Source>
              <Source_ID>2000110648/Portuguese Translation Intern Project (2020-)</Source_ID>
            </Source>
          </Note_Source>
        </Note_Sources>
      </Descriptive_Note>
    </Descriptive_Notes>
    <Record_Type>Concept</Record_Type>
    <Merged_Status>Merged</Merged_Status>
    <Sort_Order>1</Sort_Order>
    <Terms>
      <Preferred_Term>
        <Term_Text>brickworks</Term_Text>
        <Display_Name>N/A</Display_Name>
        <Historic_Flag>Current</Historic_Flag>
        <Vernacular>Undetermined</Vernacular>
        <Term_ID>1000006278</Term_ID>
        <Term_Languages>
          <Term_Language>
            <Language>70051/English</Language>
            <Preferred>Preferred</Preferred>
            <Qualifier>factories</Qualifier>
            <Term_Type>Descriptor</Term_Type>
            <Part_of_Speech>Plural Noun</Part_of_Speech>
            <Lang_Stat>Undetermined</Lang_Stat>
          </Term_Language>
        </Term_Languages>
        <Term_Contributors>
          <Term_Contributor>
            <Contributor_id>10000000/VP</Contributor_id>
            <Preferred>Preferred</Preferred>
          </Term_Contributor>
          <Term_Contributor>
            <Contributor_id>10000088/GCI</Contributor_id>
            <Preferred>Preferred</Preferred>
          </Term_Contributor>
        </Term_Contributors>
        <Term_Sources>
          <Term_Source>
            <Source>
              <Source_ID>2000046657/Avery Index (1963-)</Source_ID>
            </Source>
            <Page>(source AAT)</Page>
            <Preferred>Preferred</Preferred>
          </Term_Source>
          <Term_Source>
            <Source>
              <Source_ID>2000047206/BHA Subject Headings (1985-)</Source_ID>
            </Source>
            <Page>
            </Page>
            <Preferred>Preferred</Preferred>
          </Term_Source>
          <Term_Source>
            <Source>
              <Source_ID>2000024811/CDMARC Subjects: LCSH (1988-)</Source_ID>
            </Source>
            <Page>
            </Page>
            <Preferred>Preferred</Preferred>
          </Term_Source>
          <Term_Source>
            <Source>
              <Source_ID>2000034491/RCHME, Revised Thesaurus of Architectural Terms (1989)</Source_ID>
            </Source>
            <Page>
            </Page>
            <Preferred>Preferred</Preferred>
          </Term_Source>
          <Term_Source>
            <Source>
              <Source_ID>2000051089/AATA database (2002-) </Source_ID>
            </Source>
            <Page>121237 checked 26 January 2012</Page>
            <Preferred>Preferred</Preferred>
          </Term_Source>
          <Term_Source>
            <Source>
              <Source_ID>2000031141/Oxford English Dictionary (1989)</Source_ID>
            </Source>
            <Page>
            </Page>
            <Preferred>Alternate Preferred</Preferred>
          </Term_Source>
        </Term_Sources>
      </Preferred_Term>
      <Non-Preferred_Term>
        <Term_Text>brickwork</Term_Text>
        <Display_Name>N/A</Display_Name>
        <Historic_Flag>Current</Historic_Flag>
        <Vernacular>Undetermined</Vernacular>
        <Term_ID>1000291616</Term_ID>
        <Term_Languages>
          <Term_Language>
            <Language>70051/English</Language>
            <Preferred>Non Preferred</Preferred>
            <Qualifier>factory</Qualifier>
            <Term_Type>Alternate Descriptor</Term_Type>
            <Part_of_Speech>Singular Noun</Part_of_Speech>
            <Lang_Stat>Undetermined</Lang_Stat>
          </Term_Language>
        </Term_Languages>
        <Term_Contributors>
          <Term_Contributor>
            <Contributor_id>10000000/VP</Contributor_id>
            <Preferred>Non Preferred</Preferred>
          </Term_Contributor>
        </Term_Contributors>
        <Term_Sources>
          <Term_Source>
            <Source>
              <Source_ID>2000094828/Getty Vocabulary Program rules</Source_ID>
            </Source>
            <Page>brickwork</Page>
            <Preferred>Preferred</Preferred>
          </Term_Source>
        </Term_Sources>
      </Non-Preferred_Term>
      <Non-Preferred_Term>
        <Term_Text>brickfield</Term_Text>
        <Display_Name>N/A</Display_Name>
        <Historic_Flag>Current</Historic_Flag>
        <Vernacular>Undetermined</Vernacular>
        <Term_ID>1000265235</Term_ID>
        <Term_Languages>
          <Term_Language>
            <Language>70051/English</Language>
            <Preferred>Non Preferred</Preferred>
            <Qualifier>
            </Qualifier>
            <Term_Type>Used For Term</Term_Type>
            <Part_of_Speech>Noun</Part_of_Speech>
            <Lang_Stat>Undetermined</Lang_Stat>
          </Term_Language>
        </Term_Languages>
        <Term_Contributors>
          <Term_Contributor>
            <Contributor_id>10000000/VP</Contributor_id>
            <Preferred>Non Preferred</Preferred>
          </Term_Contributor>
        </Term_Contributors>
        <Term_Sources>
          <Term_Source>
            <Source>
              <Source_ID>2000094828/Getty Vocabulary Program rules</Source_ID>
            </Source>
            <Page>
            </Page>
            <Preferred>Non Preferred</Preferred>
          </Term_Source>
        </Term_Sources>
      </Non-Preferred_Term>
      <Non-Preferred_Term>
        <Term_Text>brickfields</Term_Text>
        <Display_Name>N/A</Display_Name>
        <Historic_Flag>Current</Historic_Flag>
        <Vernacular>Undetermined</Vernacular>
        <Term_ID>1000265236</Term_ID>
        <Term_Languages>
          <Term_Language>
            <Language>70051/English</Language>
            <Preferred>Non Preferred</Preferred>
            <Qualifier>
            </Qualifier>
            <Term_Type>Used For Term</Term_Type>
            <Part_of_Speech>Noun</Part_of_Speech>
            <Lang_Stat>Undetermined</Lang_Stat>
          </Term_Language>
        </Term_Languages>
        <Term_Contributors>
          <Term_Contributor>
            <Contributor_id>10000000/VP</Contributor_id>
            <Preferred>Non Preferred</Preferred>
          </Term_Contributor>
        </Term_Contributors>
        <Term_Sources>
          <Term_Source>
            <Source>
              <Source_ID>2000012151/Thrush, Dictionary of Mining, Mineral, and Related Terms (1968)</Source_ID>
            </Source>
            <Page>
            </Page>
            <Preferred>Preferred</Preferred>
          </Term_Source>
          <Term_Source>
            <Source>
              <Source_ID>2000042061/Webster's Third New International Dictionary (1961)</Source_ID>
            </Source>
            <Page>
            </Page>
            <Preferred>Preferred</Preferred>
          </Term_Source>
        </Term_Sources>
      </Non-Preferred_Term>
      <Non-Preferred_Term>
        <Term_Text>brick work</Term_Text>
        <Display_Name>N/A</Display_Name>
        <Historic_Flag>Current</Historic_Flag>
        <Vernacular>Undetermined</Vernacular>
        <Term_ID>1000265233</Term_ID>
        <Term_Languages>
          <Term_Language>
            <Language>70051/English</Language>
            <Preferred>Non Preferred</Preferred>
            <Qualifier>factory</Qualifier>
            <Term_Type>Used For Term</Term_Type>
            <Part_of_Speech>Noun</Part_of_Speech>
            <Lang_Stat>Undetermined</Lang_Stat>
          </Term_Language>
        </Term_Languages>
        <Term_Contributors>
          <Term_Contributor>
            <Contributor_id>10000000/VP</Contributor_id>
            <Preferred>Non Preferred</Preferred>
          </Term_Contributor>
        </Term_Contributors>
        <Term_Sources>
          <Term_Source>
            <Source>
              <Source_ID>2000094828/Getty Vocabulary Program rules</Source_ID>
            </Source>
            <Page>
            </Page>
            <Preferred>Non Preferred</Preferred>
          </Term_Source>
        </Term_Sources>
      </Non-Preferred_Term>
      <Non-Preferred_Term>
        <Term_Text>brick works</Term_Text>
        <Display_Name>N/A</Display_Name>
        <Historic_Flag>Current</Historic_Flag>
        <Vernacular>Undetermined</Vernacular>
        <Term_ID>1000265234</Term_ID>
        <Term_Languages>
          <Term_Language>
            <Language>70051/English</Language>
            <Preferred>Non Preferred</Preferred>
            <Qualifier>factories</Qualifier>
            <Term_Type>Used For Term</Term_Type>
            <Part_of_Speech>Noun</Part_of_Speech>
            <Lang_Stat>Undetermined</Lang_Stat>
          </Term_Language>
        </Term_Languages>
        <Term_Contributors>
          <Term_Contributor>
            <Contributor_id>10000000/VP</Contributor_id>
            <Preferred>Non Preferred</Preferred>
          </Term_Contributor>
        </Term_Contributors>
        <Term_Sources>
          <Term_Source>
            <Source>
              <Source_ID>2000031141/Oxford English Dictionary (1989)</Source_ID>
            </Source>
            <Page>
            </Page>
            <Preferred>Preferred</Preferred>
          </Term_Source>
          <Term_Source>
            <Source>
              <Source_ID>2000024811/CDMARC Subjects: LCSH (1988-)</Source_ID>
            </Source>
            <Page>
            </Page>
            <Preferred>Non Preferred</Preferred>
          </Term_Source>
        </Term_Sources>
      </Non-Preferred_Term>
      <Non-Preferred_Term>
        <Term_Text>brickyard</Term_Text>
        <Display_Name>N/A</Display_Name>
        <Historic_Flag>Current</Historic_Flag>
        <Vernacular>Undetermined</Vernacular>
        <Term_ID>1000265237</Term_ID>
        <Term_Languages>
          <Term_Language>
            <Language>70051/English</Language>
            <Preferred>Non Preferred</Preferred>
            <Qualifier>
            </Qualifier>
            <Term_Type>Used For Term</Term_Type>
            <Part_of_Speech>Noun</Part_of_Speech>
            <Lang_Stat>Undetermined</Lang_Stat>
          </Term_Language>
        </Term_Languages>
        <Term_Contributors>
          <Term_Contributor>
            <Contributor_id>10000000/VP</Contributor_id>
            <Preferred>Non Preferred</Preferred>
          </Term_Contributor>
        </Term_Contributors>
        <Term_Sources>
          <Term_Source>
            <Source>
              <Source_ID>2000094828/Getty Vocabulary Program rules</Source_ID>
            </Source>
            <Page>
            </Page>
            <Preferred>Non Preferred</Preferred>
          </Term_Source>
        </Term_Sources>
      </Non-Preferred_Term>
      <Non-Preferred_Term>
        <Term_Text>brickyards</Term_Text>
        <Display_Name>N/A</Display_Name>
        <Historic_Flag>Current</Historic_Flag>
        <Vernacular>Undetermined</Vernacular>
        <Term_ID>1000265238</Term_ID>
        <Term_Languages>
          <Term_Language>
            <Language>70051/English</Language>
            <Preferred>Non Preferred</Preferred>
            <Qualifier>
            </Qualifier>
            <Term_Type>Used For Term</Term_Type>
            <Part_of_Speech>Noun</Part_of_Speech>
            <Lang_Stat>Undetermined</Lang_Stat>
          </Term_Language>
        </Term_Languages>
        <Term_Contributors>
          <Term_Contributor>
            <Contributor_id>10000000/VP</Contributor_id>
            <Preferred>Non Preferred</Preferred>
          </Term_Contributor>
        </Term_Contributors>
        <Term_Sources>
          <Term_Source>
            <Source>
              <Source_ID>2000046684/Random House Unabridged Dictionary (1993)</Source_ID>
            </Source>
            <Page>
            </Page>
            <Preferred>Preferred</Preferred>
          </Term_Source>
          <Term_Source>
            <Source>
              <Source_ID>2000042061/Webster's Third New International Dictionary (1961)</Source_ID>
            </Source>
            <Page>
            </Page>
            <Preferred>Non Preferred</Preferred>
          </Term_Source>
          <Term_Source>
            <Source>
              <Source_ID>2000012151/Thrush, Dictionary of Mining, Mineral, and Related Terms (1968)</Source_ID>
            </Source>
            <Page>
            </Page>
            <Preferred>Alternate Preferred</Preferred>
          </Term_Source>
        </Term_Sources>
      </Non-Preferred_Term>
      <Non-Preferred_Term>
        <Term_Text>works, brick</Term_Text>
        <Display_Name>N/A</Display_Name>
        <Historic_Flag>Current</Historic_Flag>
        <Vernacular>Undetermined</Vernacular>
        <Term_ID>1000265240</Term_ID>
        <Term_Languages>
          <Term_Language>
            <Language>70051/English</Language>
            <Preferred>Non Preferred</Preferred>
            <Qualifier>factories</Qualifier>
            <Term_Type>Used For Term</Term_Type>
            <Part_of_Speech>Noun</Part_of_Speech>
            <Lang_Stat>Undetermined</Lang_Stat>
          </Term_Language>
        </Term_Languages>
        <Term_Contributors>
          <Term_Contributor>
            <Contributor_id>10000000/VP</Contributor_id>
            <Preferred>Non Preferred</Preferred>
          </Term_Contributor>
        </Term_Contributors>
        <Term_Sources>
          <Term_Source>
            <Source>
              <Source_ID>2000094828/Getty Vocabulary Program rules</Source_ID>
            </Source>
            <Page>
            </Page>
            <Preferred>Non Preferred</Preferred>
          </Term_Source>
        </Term_Sources>
      </Non-Preferred_Term>
      <Non-Preferred_Term>
        <Term_Text>mamposterías</Term_Text>
        <Display_Name>N/A</Display_Name>
        <Historic_Flag>Current</Historic_Flag>
        <Vernacular>Undetermined</Vernacular>
        <Term_ID>1000414737</Term_ID>
        <Term_Languages>
          <Term_Language>
            <Language>70641/Spanish</Language>
            <Preferred>Preferred</Preferred>
            <Qualifier>planta procesadora</Qualifier>
            <Term_Type>Descriptor</Term_Type>
            <Part_of_Speech>Plural Noun</Part_of_Speech>
            <Lang_Stat>Undetermined</Lang_Stat>
          </Term_Language>
        </Term_Languages>
        <Term_Contributors>
          <Term_Contributor>
            <Contributor_id>10000131/CDBP-SNPC</Contributor_id>
            <Preferred>Non Preferred</Preferred>
          </Term_Contributor>
        </Term_Contributors>
        <Term_Sources>
          <Term_Source>
            <Source>
              <Source_ID>2000051214/Comité, Plural del término en singular</Source_ID>
            </Source>
            <Page>
            </Page>
            <Preferred>Preferred</Preferred>
          </Term_Source>
        </Term_Sources>
      </Non-Preferred_Term>
      <Non-Preferred_Term>
        <Term_Text>albañilería</Term_Text>
        <Display_Name>N/A</Display_Name>
        <Historic_Flag>Current</Historic_Flag>
        <Vernacular>Undetermined</Vernacular>
        <Term_ID>1000414741</Term_ID>
        <Term_Languages>
          <Term_Language>
            <Language>70641/Spanish</Language>
            <Preferred>Non Preferred</Preferred>
            <Qualifier>
            </Qualifier>
            <Term_Type>Used For Term</Term_Type>
            <Part_of_Speech>Singular Noun</Part_of_Speech>
            <Lang_Stat>Undetermined</Lang_Stat>
          </Term_Language>
        </Term_Languages>
        <Term_Contributors>
          <Term_Contributor>
            <Contributor_id>10000131/CDBP-SNPC</Contributor_id>
            <Preferred>Non Preferred</Preferred>
          </Term_Contributor>
        </Term_Contributors>
        <Term_Sources>
          <Term_Source>
            <Source>
              <Source_ID>2000049666/Gran Enciclopedia Larousse (1973)</Source_ID>
            </Source>
            <Page>1:235</Page>
            <Preferred>Unknown</Preferred>
          </Term_Source>
        </Term_Sources>
      </Non-Preferred_Term>
      <Non-Preferred_Term>
        <Term_Text>enladrillado</Term_Text>
        <Display_Name>N/A</Display_Name>
        <Historic_Flag>Current</Historic_Flag>
        <Vernacular>Undetermined</Vernacular>
        <Term_ID>1000414740</Term_ID>
        <Term_Languages>
          <Term_Language>
            <Language>70641/Spanish</Language>
            <Preferred>Non Preferred</Preferred>
            <Qualifier>
            </Qualifier>
            <Term_Type>Used For Term</Term_Type>
            <Part_of_Speech>Singular Noun</Part_of_Speech>
            <Lang_Stat>Undetermined</Lang_Stat>
          </Term_Language>
        </Term_Languages>
        <Term_Contributors>
          <Term_Contributor>
            <Contributor_id>10000131/CDBP-SNPC</Contributor_id>
            <Preferred>Non Preferred</Preferred>
          </Term_Contributor>
        </Term_Contributors>
        <Term_Sources>
          <Term_Source>
            <Source>
              <Source_ID>2000049666/Gran Enciclopedia Larousse (1973)</Source_ID>
            </Source>
            <Page>7:235</Page>
            <Preferred>Unknown</Preferred>
          </Term_Source>
        </Term_Sources>
      </Non-Preferred_Term>
      <Non-Preferred_Term>
        <Term_Text>mampostería</Term_Text>
        <Display_Name>N/A</Display_Name>
        <Historic_Flag>Current</Historic_Flag>
        <Vernacular>Undetermined</Vernacular>
        <Term_ID>1000414738</Term_ID>
        <Term_Languages>
          <Term_Language>
            <Language>70641/Spanish</Language>
            <Preferred>Non Preferred</Preferred>
            <Qualifier>planta procesadora</Qualifier>
            <Term_Type>Alternate Descriptor</Term_Type>
            <Part_of_Speech>Singular Noun</Part_of_Speech>
            <Lang_Stat>Undetermined</Lang_Stat>
          </Term_Language>
        </Term_Languages>
        <Term_Contributors>
          <Term_Contributor>
            <Contributor_id>10000131/CDBP-SNPC</Contributor_id>
            <Preferred>Preferred</Preferred>
          </Term_Contributor>
        </Term_Contributors>
        <Term_Sources>
          <Term_Source>
            <Source>
              <Source_ID>2000049666/Gran Enciclopedia Larousse (1973)</Source_ID>
            </Source>
            <Page>12:892</Page>
            <Preferred>Unknown</Preferred>
          </Term_Source>
          <Term_Source>
            <Source>
              <Source_ID>2000051218/Alvarez et al., Diccionario de la decoración (1968)</Source_ID>
            </Source>
            <Page>390</Page>
            <Preferred>Unknown</Preferred>
          </Term_Source>
        </Term_Sources>
      </Non-Preferred_Term>
      <Non-Preferred_Term>
        <Term_Text>masonería</Term_Text>
        <Display_Name>N/A</Display_Name>
        <Historic_Flag>Current</Historic_Flag>
        <Vernacular>Undetermined</Vernacular>
        <Term_ID>1000414739</Term_ID>
        <Term_Languages>
          <Term_Language>
            <Language>70641/Spanish</Language>
            <Preferred>Non Preferred</Preferred>
            <Qualifier>
            </Qualifier>
            <Term_Type>Used For Term</Term_Type>
            <Part_of_Speech>Singular Noun</Part_of_Speech>
            <Lang_Stat>Undetermined</Lang_Stat>
          </Term_Language>
        </Term_Languages>
        <Term_Contributors>
          <Term_Contributor>
            <Contributor_id>10000131/CDBP-SNPC</Contributor_id>
            <Preferred>Non Preferred</Preferred>
          </Term_Contributor>
        </Term_Contributors>
        <Term_Sources>
          <Term_Source>
            <Source>
              <Source_ID>2000049666/Gran Enciclopedia Larousse (1973)</Source_ID>
            </Source>
            <Page>13:80</Page>
            <Preferred>Unknown</Preferred>
          </Term_Source>
        </Term_Sources>
      </Non-Preferred_Term>
      <Non-Preferred_Term>
        <Term_Text>obra de fábrica</Term_Text>
        <Display_Name>N/A</Display_Name>
        <Historic_Flag>Current</Historic_Flag>
        <Vernacular>Undetermined</Vernacular>
        <Term_ID>1000414742</Term_ID>
        <Term_Languages>
          <Term_Language>
            <Language>70641/Spanish</Language>
            <Preferred>Non Preferred</Preferred>
            <Qualifier>
            </Qualifier>
            <Term_Type>Used For Term</Term_Type>
            <Part_of_Speech>Singular Noun</Part_of_Speech>
            <Lang_Stat>Undetermined</Lang_Stat>
          </Term_Language>
        </Term_Languages>
        <Term_Contributors>
          <Term_Contributor>
            <Contributor_id>10000131/CDBP-SNPC</Contributor_id>
            <Preferred>Non Preferred</Preferred>
          </Term_Contributor>
        </Term_Contributors>
        <Term_Sources>
          <Term_Source>
            <Source>
              <Source_ID>2000049666/Gran Enciclopedia Larousse (1973)</Source_ID>
            </Source>
            <Page>13:80</Page>
            <Preferred>Unknown</Preferred>
          </Term_Source>
        </Term_Sources>
      </Non-Preferred_Term>
      <Non-Preferred_Term>
        <Term_Text>steenfabrieken</Term_Text>
        <Display_Name>N/A</Display_Name>
        <Historic_Flag>Current</Historic_Flag>
        <Vernacular>Undetermined</Vernacular>
        <Term_ID>1000467113</Term_ID>
        <Term_Languages>
          <Term_Language>
            <Language>70261/Dutch</Language>
            <Preferred>Non Preferred</Preferred>
            <Qualifier>
            </Qualifier>
            <Term_Type>Used For Term</Term_Type>
            <Part_of_Speech>Undetermined</Part_of_Speech>
            <Lang_Stat>Undetermined</Lang_Stat>
          </Term_Language>
        </Term_Languages>
        <Term_Contributors>
          <Term_Contributor>
            <Contributor_id>10000205/AAT-Ned</Contributor_id>
            <Preferred>Preferred</Preferred>
          </Term_Contributor>
        </Term_Contributors>
        <Term_Sources>
          <Term_Source>
            <Source>
              <Source_ID>2000113770/AAT-Ned (1994-)</Source_ID>
            </Source>
            <Page>
            </Page>
            <Preferred>Preferred</Preferred>
          </Term_Source>
          <Term_Source>
            <Source>
              <Source_ID>2000052374/Polytechnisch woordenboek En-Ne (1991)</Source_ID>
            </Source>
            <Page>
            </Page>
            <Preferred>Unknown</Preferred>
          </Term_Source>
        </Term_Sources>
      </Non-Preferred_Term>
      <Non-Preferred_Term>
        <Term_Text>steenbakkerijen</Term_Text>
        <Display_Name>N/A</Display_Name>
        <Historic_Flag>Current</Historic_Flag>
        <Vernacular>Undetermined</Vernacular>
        <Term_ID>1000467115</Term_ID>
        <Term_Languages>
          <Term_Language>
            <Language>70261/Dutch</Language>
            <Preferred>Preferred</Preferred>
            <Qualifier>
            </Qualifier>
            <Term_Type>Descriptor</Term_Type>
            <Part_of_Speech>Undetermined</Part_of_Speech>
            <Lang_Stat>Undetermined</Lang_Stat>
          </Term_Language>
        </Term_Languages>
        <Term_Contributors>
          <Term_Contributor>
            <Contributor_id>10000205/AAT-Ned</Contributor_id>
            <Preferred>Non Preferred</Preferred>
          </Term_Contributor>
        </Term_Contributors>
        <Term_Sources>
          <Term_Source>
            <Source>
              <Source_ID>2000113770/AAT-Ned (1994-)</Source_ID>
            </Source>
            <Page>
            </Page>
            <Preferred>Unknown</Preferred>
          </Term_Source>
          <Term_Source>
            <Source>
              <Source_ID>2000052374/Polytechnisch woordenboek En-Ne (1991)</Source_ID>
            </Source>
            <Page>
            </Page>
            <Preferred>Unknown</Preferred>
          </Term_Source>
        </Term_Sources>
      </Non-Preferred_Term>
      <Non-Preferred_Term>
        <Term_Text>steenbakkerij</Term_Text>
        <Display_Name>N/A</Display_Name>
        <Historic_Flag>Current</Historic_Flag>
        <Vernacular>Undetermined</Vernacular>
        <Term_ID>1000609890</Term_ID>
        <Term_Languages>
          <Term_Language>
            <Language>70261/Dutch</Language>
            <Preferred>Non Preferred</Preferred>
            <Qualifier>
            </Qualifier>
            <Term_Type>Alternate Descriptor</Term_Type>
            <Part_of_Speech>Undetermined</Part_of_Speech>
            <Lang_Stat>Undetermined</Lang_Stat>
          </Term_Language>
        </Term_Languages>
        <Term_Contributors>
          <Term_Contributor>
            <Contributor_id>10000205/AAT-Ned</Contributor_id>
            <Preferred>Non Preferred</Preferred>
          </Term_Contributor>
        </Term_Contributors>
        <Term_Sources>
          <Term_Source>
            <Source>
              <Source_ID>2000052374/Polytechnisch woordenboek En-Ne (1991)</Source_ID>
            </Source>
            <Page>
            </Page>
            <Preferred>Unknown</Preferred>
          </Term_Source>
        </Term_Sources>
      </Non-Preferred_Term>
      <Non-Preferred_Term>
        <Term_Text>Ziegeleien</Term_Text>
        <Display_Name>N/A</Display_Name>
        <Historic_Flag>Current</Historic_Flag>
        <Vernacular>Undetermined</Vernacular>
        <Term_ID>1000652233</Term_ID>
        <Term_Languages>
          <Term_Language>
            <Language>70101/German</Language>
            <Preferred>Non Preferred</Preferred>
            <Qualifier>
            </Qualifier>
            <Term_Type>Descriptor</Term_Type>
            <Part_of_Speech>Plural Noun</Part_of_Speech>
            <Lang_Stat>
            </Lang_Stat>
          </Term_Language>
        </Term_Languages>
        <Term_Contributors>
          <Term_Contributor>
            <Contributor_id>10000232/IfM-SMB-PK</Contributor_id>
            <Preferred>Non Preferred</Preferred>
          </Term_Contributor>
        </Term_Contributors>
        <Term_Sources>
          <Term_Source>
            <Source>
              <Source_ID>2000083679/DWDS - Digitales Wörterbuch der deutschen Sprache [online] (2008-)</Source_ID>
            </Source>
            <Page>http://www.dwds.de/?view=1&amp;qu=Ziegelei</Page>
            <Preferred>Preferred</Preferred>
          </Term_Source>
        </Term_Sources>
      </Non-Preferred_Term>
      <Non-Preferred_Term>
        <Term_Text>Ziegelbrennerei</Term_Text>
        <Display_Name>N/A</Display_Name>
        <Historic_Flag>Current</Historic_Flag>
        <Vernacular>Undetermined</Vernacular>
        <Term_ID>1000652238</Term_ID>
        <Term_Languages>
          <Term_Language>
            <Language>70101/German</Language>
            <Preferred>Non Preferred</Preferred>
            <Qualifier>
            </Qualifier>
            <Term_Type>Used For Term</Term_Type>
            <Part_of_Speech>Singular Noun</Part_of_Speech>
            <Lang_Stat>
            </Lang_Stat>
          </Term_Language>
        </Term_Languages>
        <Term_Contributors>
          <Term_Contributor>
            <Contributor_id>10000232/IfM-SMB-PK</Contributor_id>
            <Preferred>Non Preferred</Preferred>
          </Term_Contributor>
        </Term_Contributors>
        <Term_Sources>
          <Term_Source>
            <Source>
              <Source_ID>2000083634/Duden [online] (2011-)</Source_ID>
            </Source>
            <Page>http://www.duden.de/node/745980/revisions/1178309/view</Page>
            <Preferred>Unknown</Preferred>
          </Term_Source>
        </Term_Sources>
      </Non-Preferred_Term>
      <Non-Preferred_Term>
        <Term_Text>Ziegelbrennereien</Term_Text>
        <Display_Name>N/A</Display_Name>
        <Historic_Flag>Current</Historic_Flag>
        <Vernacular>Undetermined</Vernacular>
        <Term_ID>1000652237</Term_ID>
        <Term_Languages>
          <Term_Language>
            <Language>70101/German</Language>
            <Preferred>Non Preferred</Preferred>
            <Qualifier>
            </Qualifier>
            <Term_Type>Used For Term</Term_Type>
            <Part_of_Speech>Plural Noun</Part_of_Speech>
            <Lang_Stat>
            </Lang_Stat>
          </Term_Language>
        </Term_Languages>
        <Term_Contributors>
          <Term_Contributor>
            <Contributor_id>10000232/IfM-SMB-PK</Contributor_id>
            <Preferred>Non Preferred</Preferred>
          </Term_Contributor>
        </Term_Contributors>
        <Term_Sources>
          <Term_Source>
            <Source>
              <Source_ID>2000083634/Duden [online] (2011-)</Source_ID>
            </Source>
            <Page>http://www.duden.de/node/745980/revisions/1178309/view</Page>
            <Preferred>Unknown</Preferred>
          </Term_Source>
        </Term_Sources>
      </Non-Preferred_Term>
      <Non-Preferred_Term>
        <Term_Text>Ziegelei</Term_Text>
        <Display_Name>N/A</Display_Name>
        <Historic_Flag>Current</Historic_Flag>
        <Vernacular>Undetermined</Vernacular>
        <Term_ID>1000652234</Term_ID>
        <Term_Languages>
          <Term_Language>
            <Language>70101/German</Language>
            <Preferred>Preferred</Preferred>
            <Qualifier>
            </Qualifier>
            <Term_Type>Alternate Descriptor</Term_Type>
            <Part_of_Speech>Singular Noun</Part_of_Speech>
            <Lang_Stat>
            </Lang_Stat>
          </Term_Language>
        </Term_Languages>
        <Term_Contributors>
          <Term_Contributor>
            <Contributor_id>10000232/IfM-SMB-PK</Contributor_id>
            <Preferred>Preferred</Preferred>
          </Term_Contributor>
        </Term_Contributors>
        <Term_Sources>
          <Term_Source>
            <Source>
              <Source_ID>2000083679/DWDS - Digitales Wörterbuch der deutschen Sprache [online] (2008-)</Source_ID>
            </Source>
            <Page>http://www.dwds.de/?view=1&amp;qu=Ziegelei</Page>
            <Preferred>Unknown</Preferred>
          </Term_Source>
          <Term_Source>
            <Source>
              <Source_ID>2000083634/Duden [online] (2011-)</Source_ID>
            </Source>
            <Page>http://www.duden.de/node/745842/revisions/1218452/view</Page>
            <Preferred>Unknown</Preferred>
          </Term_Source>
          <Term_Source>
            <Source>
              <Source_ID>2000083630/GND - Gemeinsame Normdatei</Source_ID>
            </Source>
            <Page>http://d-nb.info/gnd/4190777-2</Page>
            <Preferred>Unknown</Preferred>
          </Term_Source>
        </Term_Sources>
      </Non-Preferred_Term>
      <Non-Preferred_Term>
        <Term_Text>Ziegelfabrik</Term_Text>
        <Display_Name>N/A</Display_Name>
        <Historic_Flag>Current</Historic_Flag>
        <Vernacular>Undetermined</Vernacular>
        <Term_ID>1000652236</Term_ID>
        <Term_Languages>
          <Term_Language>
            <Language>70101/German</Language>
            <Preferred>Non Preferred</Preferred>
            <Qualifier>
            </Qualifier>
            <Term_Type>Used For Term</Term_Type>
            <Part_of_Speech>Singular Noun</Part_of_Speech>
            <Lang_Stat>
            </Lang_Stat>
          </Term_Language>
        </Term_Languages>
        <Term_Contributors>
          <Term_Contributor>
            <Contributor_id>10000232/IfM-SMB-PK</Contributor_id>
            <Preferred>Non Preferred</Preferred>
          </Term_Contributor>
        </Term_Contributors>
        <Term_Sources>
          <Term_Source>
            <Source>
              <Source_ID>2000083657/Wortschatz Universität Leipzig [online] (1998 -)</Source_ID>
            </Source>
            <Page>"Ziegelfabrik", accessed 2 August 2014</Page>
            <Preferred>Unknown</Preferred>
          </Term_Source>
        </Term_Sources>
      </Non-Preferred_Term>
      <Non-Preferred_Term>
        <Term_Text>Ziegelfabriken</Term_Text>
        <Display_Name>N/A</Display_Name>
        <Historic_Flag>Current</Historic_Flag>
        <Vernacular>Undetermined</Vernacular>
        <Term_ID>1000652235</Term_ID>
        <Term_Languages>
          <Term_Language>
            <Language>70101/German</Language>
            <Preferred>Non Preferred</Preferred>
            <Qualifier>
            </Qualifier>
            <Term_Type>Used For Term</Term_Type>
            <Part_of_Speech>Plural Noun</Part_of_Speech>
            <Lang_Stat>
            </Lang_Stat>
          </Term_Language>
        </Term_Languages>
        <Term_Contributors>
          <Term_Contributor>
            <Contributor_id>10000232/IfM-SMB-PK</Contributor_id>
            <Preferred>Non Preferred</Preferred>
          </Term_Contributor>
        </Term_Contributors>
        <Term_Sources>
          <Term_Source>
            <Source>
              <Source_ID>2000122169/AAT-Deutsch (2012-)</Source_ID>
            </Source>
            <Page>
            </Page>
            <Preferred>Unknown</Preferred>
          </Term_Source>
        </Term_Sources>
      </Non-Preferred_Term>
      <Non-Preferred_Term>
        <Term_Text>alvenarias</Term_Text>
        <Display_Name>N/A</Display_Name>
        <Historic_Flag>Current</Historic_Flag>
        <Vernacular>Undetermined</Vernacular>
        <Term_ID>1000886526</Term_ID>
        <Term_Languages>
          <Term_Language>
            <Language>70543/Portuguese</Language>
            <Preferred>Preferred</Preferred>
            <Qualifier>fábricas</Qualifier>
            <Term_Type>Descriptor</Term_Type>
            <Part_of_Speech>Plural Noun</Part_of_Speech>
            <Lang_Stat>Undetermined</Lang_Stat>
          </Term_Language>
        </Term_Languages>
        <Term_Contributors>
          <Term_Contributor>
            <Contributor_id>10000179/VP-intern</Contributor_id>
            <Preferred>Non Preferred</Preferred>
          </Term_Contributor>
          <Term_Contributor>
            <Contributor_id>10000000/VP</Contributor_id>
            <Preferred>Non Preferred</Preferred>
          </Term_Contributor>
        </Term_Contributors>
        <Term_Sources>
          <Term_Source>
            <Source>
              <Source_ID>2000110648/Portuguese Translation Intern Project (2020-)</Source_ID>
            </Source>
            <Page>
            </Page>
            <Preferred>Non Preferred</Preferred>
          </Term_Source>
          <Term_Source>
            <Source>
              <Source_ID>2000110657/Michaelis Moderno Dicionário Inglês &amp; Português (2016)</Source_ID>
            </Source>
            <Page>accessed on 30 August 2021</Page>
            <Preferred>Non Preferred</Preferred>
          </Term_Source>
          <Term_Source>
            <Source>
              <Source_ID>2000113209/Houaiss e Villar. Dicionário Houaiss da língua portuguesa (2009)</Source_ID>
            </Source>
            <Page>106</Page>
            <Preferred>Non Preferred</Preferred>
          </Term_Source>
        </Term_Sources>
      </Non-Preferred_Term>
      <Non-Preferred_Term>
        <Term_Text>alvenaria</Term_Text>
        <Display_Name>N/A</Display_Name>
        <Historic_Flag>Current</Historic_Flag>
        <Vernacular>Undetermined</Vernacular>
        <Term_ID>1000886527</Term_ID>
        <Term_Languages>
          <Term_Language>
            <Language>70543/Portuguese</Language>
            <Preferred>Non Preferred</Preferred>
            <Qualifier>fábrica</Qualifier>
            <Term_Type>Alternate Descriptor</Term_Type>
            <Part_of_Speech>Singular Noun</Part_of_Speech>
            <Lang_Stat>Undetermined</Lang_Stat>
          </Term_Language>
        </Term_Languages>
        <Term_Contributors>
          <Term_Contributor>
            <Contributor_id>10000000/VP</Contributor_id>
            <Preferred>Non Preferred</Preferred>
          </Term_Contributor>
          <Term_Contributor>
            <Contributor_id>10000179/VP-intern</Contributor_id>
            <Preferred>Non Preferred</Preferred>
          </Term_Contributor>
        </Term_Contributors>
        <Term_Sources>
          <Term_Source>
            <Source>
              <Source_ID>2000113209/Houaiss e Villar. Dicionário Houaiss da língua portuguesa (2009)</Source_ID>
            </Source>
            <Page>106</Page>
            <Preferred>Non Preferred</Preferred>
          </Term_Source>
          <Term_Source>
            <Source>
              <Source_ID>2000110657/Michaelis Moderno Dicionário Inglês &amp; Português (2016)</Source_ID>
            </Source>
            <Page>accessed on 30 August 2021</Page>
            <Preferred>Non Preferred</Preferred>
          </Term_Source>
          <Term_Source>
            <Source>
              <Source_ID>2000110648/Portuguese Translation Intern Project (2020-)</Source_ID>
            </Source>
            <Page>
            </Page>
            <Preferred>Non Preferred</Preferred>
          </Term_Source>
        </Term_Sources>
      </Non-Preferred_Term>
    </Terms>
    <Associative_Relationships>
      <Associative_Relationship>
        <Relationship_Type>locus/setting for</Relationship_Type>
        <Related_Subject_ID>
          <VP_Subject_ID>300220231</VP_Subject_ID>
        </Related_Subject_ID>
        <Historic_Flag>Current</Historic_Flag>
      </Associative_Relationship>
      <Associative_Relationship>
        <Relationship_Type>locus/setting for</Relationship_Type>
        <Related_Subject_ID>
          <VP_Subject_ID>300025282</VP_Subject_ID>
        </Related_Subject_ID>
        <Historic_Flag>Current</Historic_Flag>
      </Associative_Relationship>
      <Associative_Relationship>
        <Relationship_Type>locus/setting for</Relationship_Type>
        <Related_Subject_ID>
          <VP_Subject_ID>300010463</VP_Subject_ID>
        </Related_Subject_ID>
        <Historic_Flag>Current</Historic_Flag>
      </Associative_Relationship>
    </Associative_Relationships>
    <Subject_Contributors>
      <Subject_Contributor>
        <Contributor_id>10000000/VP</Contributor_id>
      </Subject_Contributor>
      <Subject_Contributor>
        <Contributor_id>10000088/GCI</Contributor_id>
      </Subject_Contributor>
      <Subject_Contributor>
        <Contributor_id>10000131/CDBP-SNPC</Contributor_id>
      </Subject_Contributor>
      <Subject_Contributor>
        <Contributor_id>10000205/AAT-Ned</Contributor_id>
      </Subject_Contributor>
      <Subject_Contributor>
        <Contributor_id>10000232/IfM-SMB-PK</Contributor_id>
      </Subject_Contributor>
    </Subject_Contributors>
    <Subject_Sources>
      <Subject_Source>
        <Source>
          <Source_ID>2000051089/AATA database (2002-) </Source_ID>
        </Source>
      </Subject_Source>
      <Subject_Source>
        <Source>
          <Source_ID>2000035111/RIBA, Architectural Keywords (1982)</Source_ID>
        </Source>
      </Subject_Source>
      <Subject_Source>
        <Source>
          <Source_ID>2000052374/Polytechnisch woordenboek En-Ne (1991)</Source_ID>
        </Source>
      </Subject_Source>
    </Subject_Sources>
  </Subject>
</Vocabulary>