<?xml version="1.0" encoding="utf-8"?>
<Vocabulary xmlns:xsi="http://www.w3.org/2001/XMLSchema-instance" xsi:noNamespaceSchemaLocation="http://vocabsservices.getty.edu/Schemas/AAT/AATGetSubject.xsd">
  <Subject Subject_ID="300254182">
    <Parent_Relationships>
      <Preferred_Parent>
        <Parent_Subject_ID>300053692</Parent_Subject_ID>
        <Relationship_Type>Parent/Child</Relationship_Type>
        <Historic_Flag>Current</Historic_Flag>
        <Parent_String>protective processes and techniques [300053692], processes and techniques by specific type [300053003], Processes and Techniques (hierarchy name) [300053001], Activities Facet [300264090]</Parent_String>
        <Hier_Rel_Type>Genus/Species-BTG</Hier_Rel_Type>
      </Preferred_Parent>
    </Parent_Relationships>
    <Descriptive_Notes>
      <Descriptive_Note>
        <Note_Text>Strengthening elements of the built environment against attack, providing them with some means of defense, or protecting them with fortifications or fortification elements.</Note_Text>
        <Note_Language>English</Note_Language>
        <Note_Contributors>
          <Note_Contributor>
            <Contributor_id>10000000/VP</Contributor_id>
          </Note_Contributor>
        </Note_Contributors>
        <Note_Sources>
          <Note_Source>
            <Source>
              <Source_ID>2000099620/Legacy AAT data</Source_ID>
            </Source>
          </Note_Source>
        </Note_Sources>
      </Descriptive_Note>
      <Descriptive_Note>
        <Note_Text>Fortalecimiento de elementos de un entorno construido contra ataques, dándole los medios de defensa o protegiéndolos con fortificaciones o elementos de fortificación.</Note_Text>
        <Note_Language>Spanish</Note_Language>
        <Note_Contributors>
          <Note_Contributor>
            <Contributor_id>10000131/CDBP-SNPC</Contributor_id>
          </Note_Contributor>
        </Note_Contributors>
        <Note_Sources>
          <Note_Source>
            <Source>
              <Source_ID>2000051034/TAA database (2000-)</Source_ID>
            </Source>
          </Note_Source>
        </Note_Sources>
      </Descriptive_Note>
      <Descriptive_Note>
        <Note_Text>Het sterker maken van elementen in de bebouwde omgeving voor het geval dat er zich een aanval voordoet, door ze te voorzien van enige verdedigingsmiddelen, of door ze te verstevigen met versterkingen of versterkingselementen</Note_Text>
        <Note_Language>Dutch</Note_Language>
        <Note_Contributors>
          <Note_Contributor>
            <Contributor_id>10000205/AAT-Ned</Contributor_id>
          </Note_Contributor>
        </Note_Contributors>
        <Note_Sources>
          <Note_Source>
            <Source>
              <Source_ID>2000113770/AAT-Ned (1994-)</Source_ID>
            </Source>
          </Note_Source>
          <Note_Source>
            <Source>
              <Source_ID>2000099099/Van Dale groot woordenboek (1994)</Source_ID>
            </Source>
          </Note_Source>
        </Note_Sources>
      </Descriptive_Note>
      <Descriptive_Note>
        <Note_Text>提供某些防護措施或築城，鞏固加強建築環境元素，來保護建築物抵擋攻擊。
</Note_Text>
        <Note_Language>Chinese (traditional)</Note_Language>
        <Note_Contributors>
          <Note_Contributor>
            <Contributor_id>10000250/AS-Academia Sinica</Contributor_id>
          </Note_Contributor>
        </Note_Contributors>
        <Note_Sources>
          <Note_Source>
            <Source>
              <Source_ID>2000079740/AS-Academia Sinica data (2014-)</Source_ID>
            </Source>
          </Note_Source>
        </Note_Sources>
      </Descriptive_Note>
    </Descriptive_Notes>
    <Record_Type>Concept</Record_Type>
    <Merged_Status>Merged</Merged_Status>
    <Sort_Order>1</Sort_Order>
    <Terms>
      <Preferred_Term>
        <Term_Text>fortifying</Term_Text>
        <Display_Name>N/A</Display_Name>
        <Historic_Flag>Current</Historic_Flag>
        <Vernacular>Undetermined</Vernacular>
        <Term_ID>1000254182</Term_ID>
        <Term_Languages>
          <Term_Language>
            <Language>70051/English</Language>
            <Preferred>Preferred</Preferred>
            <Qualifier>
            </Qualifier>
            <Term_Type>Descriptor</Term_Type>
            <Part_of_Speech>Undetermined</Part_of_Speech>
            <Lang_Stat>Undetermined</Lang_Stat>
          </Term_Language>
        </Term_Languages>
        <Term_Contributors>
          <Term_Contributor>
            <Contributor_id>10000000/VP</Contributor_id>
            <Preferred>Preferred</Preferred>
          </Term_Contributor>
        </Term_Contributors>
        <Term_Sources>
          <Term_Source>
            <Source>
              <Source_ID>2000031141/Oxford English Dictionary (1989)</Source_ID>
            </Source>
            <Page>
            </Page>
            <Preferred>Alternate Preferred</Preferred>
          </Term_Source>
          <Term_Source>
            <Source>
              <Source_ID>2000046684/Random House Unabridged Dictionary (1993)</Source_ID>
            </Source>
            <Page>
            </Page>
            <Preferred>Alternate Preferred</Preferred>
          </Term_Source>
        </Term_Sources>
      </Preferred_Term>
      <Non-Preferred_Term>
        <Term_Text>fortified</Term_Text>
        <Display_Name>N/A</Display_Name>
        <Historic_Flag>Current</Historic_Flag>
        <Vernacular>Undetermined</Vernacular>
        <Term_ID>1000284249</Term_ID>
        <Term_Languages>
          <Term_Language>
            <Language>70051/English</Language>
            <Preferred>Non Preferred</Preferred>
            <Qualifier>
            </Qualifier>
            <Term_Type>Alternate Descriptor</Term_Type>
            <Part_of_Speech>Undetermined</Part_of_Speech>
            <Lang_Stat>Undetermined</Lang_Stat>
          </Term_Language>
        </Term_Languages>
        <Term_Contributors>
          <Term_Contributor>
            <Contributor_id>10000000/VP</Contributor_id>
            <Preferred>Non Preferred</Preferred>
          </Term_Contributor>
        </Term_Contributors>
        <Term_Sources>
          <Term_Source>
            <Source>
              <Source_ID>2000031141/Oxford English Dictionary (1989)</Source_ID>
            </Source>
            <Page>
            </Page>
            <Preferred>Preferred</Preferred>
          </Term_Source>
          <Term_Source>
            <Source>
              <Source_ID>2000046684/Random House Unabridged Dictionary (1993)</Source_ID>
            </Source>
            <Page>
            </Page>
            <Preferred>Preferred</Preferred>
          </Term_Source>
        </Term_Sources>
      </Non-Preferred_Term>
      <Non-Preferred_Term>
        <Term_Text>versterken</Term_Text>
        <Display_Name>N/A</Display_Name>
        <Historic_Flag>Current</Historic_Flag>
        <Vernacular>Undetermined</Vernacular>
        <Term_ID>1000509499</Term_ID>
        <Term_Languages>
          <Term_Language>
            <Language>70261/Dutch</Language>
            <Preferred>Preferred</Preferred>
            <Qualifier>fortificeren</Qualifier>
            <Term_Type>Descriptor</Term_Type>
            <Part_of_Speech>Undetermined</Part_of_Speech>
            <Lang_Stat>Undetermined</Lang_Stat>
          </Term_Language>
        </Term_Languages>
        <Term_Contributors>
          <Term_Contributor>
            <Contributor_id>10000205/AAT-Ned</Contributor_id>
            <Preferred>Preferred</Preferred>
          </Term_Contributor>
        </Term_Contributors>
        <Term_Sources>
          <Term_Source>
            <Source>
              <Source_ID>2000113770/AAT-Ned (1994-)</Source_ID>
            </Source>
            <Page>
            </Page>
            <Preferred>Preferred</Preferred>
          </Term_Source>
          <Term_Source>
            <Source>
              <Source_ID>2000099099/Van Dale groot woordenboek (1994)</Source_ID>
            </Source>
            <Page>
            </Page>
            <Preferred>Unknown</Preferred>
          </Term_Source>
        </Term_Sources>
      </Non-Preferred_Term>
      <Non-Preferred_Term>
        <Term_Text>fortificado</Term_Text>
        <Display_Name>N/A</Display_Name>
        <Historic_Flag>Current</Historic_Flag>
        <Vernacular>Undetermined</Vernacular>
        <Term_ID>1000453553</Term_ID>
        <Term_Languages>
          <Term_Language>
            <Language>70641/Spanish</Language>
            <Preferred>Preferred</Preferred>
            <Qualifier>
            </Qualifier>
            <Term_Type>Descriptor</Term_Type>
            <Part_of_Speech>Undetermined</Part_of_Speech>
            <Lang_Stat>Undetermined</Lang_Stat>
          </Term_Language>
        </Term_Languages>
        <Term_Contributors>
          <Term_Contributor>
            <Contributor_id>10000131/CDBP-SNPC</Contributor_id>
            <Preferred>Preferred</Preferred>
          </Term_Contributor>
          <Term_Contributor>
            <Contributor_id>10000000/VP</Contributor_id>
            <Preferred>Non Preferred</Preferred>
          </Term_Contributor>
        </Term_Contributors>
        <Term_Sources>
          <Term_Source>
            <Source>
              <Source_ID>2000048810/Moliner, Diccionario de uso del español (2004)</Source_ID>
            </Source>
            <Page>I:1330</Page>
            <Preferred>Preferred</Preferred>
          </Term_Source>
          <Term_Source>
            <Source>
              <Source_ID>2000051034/TAA database (2000-)</Source_ID>
            </Source>
            <Page>
            </Page>
            <Preferred>Non Preferred</Preferred>
          </Term_Source>
        </Term_Sources>
      </Non-Preferred_Term>
      <Non-Preferred_Term>
        <Term_Text>versterkt</Term_Text>
        <Display_Name>N/A</Display_Name>
        <Historic_Flag>Current</Historic_Flag>
        <Vernacular>Undetermined</Vernacular>
        <Term_ID>1000612030</Term_ID>
        <Term_Languages>
          <Term_Language>
            <Language>70261/Dutch</Language>
            <Preferred>Non Preferred</Preferred>
            <Qualifier>
            </Qualifier>
            <Term_Type>Alternate Descriptor</Term_Type>
            <Part_of_Speech>Undetermined</Part_of_Speech>
            <Lang_Stat>Undetermined</Lang_Stat>
          </Term_Language>
        </Term_Languages>
        <Term_Contributors>
          <Term_Contributor>
            <Contributor_id>10000205/AAT-Ned</Contributor_id>
            <Preferred>Non Preferred</Preferred>
          </Term_Contributor>
        </Term_Contributors>
        <Term_Sources>
          <Term_Source>
            <Source>
              <Source_ID>2000099099/Van Dale groot woordenboek (1994)</Source_ID>
            </Source>
            <Page>
            </Page>
            <Preferred>Unknown</Preferred>
          </Term_Source>
        </Term_Sources>
      </Non-Preferred_Term>
      <Non-Preferred_Term>
        <Term_Text>強化</Term_Text>
        <Display_Name>N/A</Display_Name>
        <Historic_Flag>Current</Historic_Flag>
        <Vernacular>Undetermined</Vernacular>
        <Term_ID>1000894500</Term_ID>
        <Term_Languages>
          <Term_Language>
            <Language>72551/Chinese (traditional)</Language>
            <Preferred>Preferred</Preferred>
            <Qualifier>保護建築物</Qualifier>
            <Term_Type>Descriptor</Term_Type>
            <Part_of_Speech>Undetermined</Part_of_Speech>
            <Lang_Stat>Undetermined</Lang_Stat>
          </Term_Language>
        </Term_Languages>
        <Term_Contributors>
          <Term_Contributor>
            <Contributor_id>10000250/AS-Academia Sinica</Contributor_id>
            <Preferred>Preferred</Preferred>
          </Term_Contributor>
        </Term_Contributors>
        <Term_Sources>
          <Term_Source>
            <Source>
              <Source_ID>2000119189/朗文當代大辭典</Source_ID>
            </Source>
            <Page>676</Page>
            <Preferred>Preferred</Preferred>
          </Term_Source>
          <Term_Source>
            <Source>
              <Source_ID>2000119190/智慧藏百科全書網</Source_ID>
            </Source>
            <Page>2009.11.16</Page>
            <Preferred>Preferred</Preferred>
          </Term_Source>
          <Term_Source>
            <Source>
              <Source_ID>2000119191/牛津當代大辭典</Source_ID>
            </Source>
            <Page>689</Page>
            <Preferred>Preferred</Preferred>
          </Term_Source>
        </Term_Sources>
      </Non-Preferred_Term>
      <Non-Preferred_Term>
        <Term_Text>ch'iang hua</Term_Text>
        <Display_Name>N/A</Display_Name>
        <Historic_Flag>Current</Historic_Flag>
        <Vernacular>Undetermined</Vernacular>
        <Term_ID>1000894503</Term_ID>
        <Term_Languages>
          <Term_Language>
            <Language>72582/Chinese (transliterated Wade-Giles)</Language>
            <Preferred>Preferred</Preferred>
            <Qualifier>
            </Qualifier>
            <Term_Type>Used For Term</Term_Type>
            <Part_of_Speech>Undetermined</Part_of_Speech>
            <Lang_Stat>Undetermined</Lang_Stat>
          </Term_Language>
        </Term_Languages>
        <Term_Contributors>
          <Term_Contributor>
            <Contributor_id>10000250/AS-Academia Sinica</Contributor_id>
            <Preferred>Non Preferred</Preferred>
          </Term_Contributor>
        </Term_Contributors>
        <Term_Sources>
          <Term_Source>
            <Source>
              <Source_ID>2000079740/AS-Academia Sinica data (2014-)</Source_ID>
            </Source>
            <Page>
            </Page>
            <Preferred>Non Preferred</Preferred>
          </Term_Source>
        </Term_Sources>
      </Non-Preferred_Term>
      <Non-Preferred_Term>
        <Term_Text>qiang hua</Term_Text>
        <Display_Name>N/A</Display_Name>
        <Historic_Flag>Current</Historic_Flag>
        <Vernacular>Undetermined</Vernacular>
        <Term_ID>1000894501</Term_ID>
        <Term_Languages>
          <Term_Language>
            <Language>72586/Chinese (transliterated Pinyin without tones)</Language>
            <Preferred>Preferred</Preferred>
            <Qualifier>
            </Qualifier>
            <Term_Type>Used For Term</Term_Type>
            <Part_of_Speech>Undetermined</Part_of_Speech>
            <Lang_Stat>Undetermined</Lang_Stat>
          </Term_Language>
        </Term_Languages>
        <Term_Contributors>
          <Term_Contributor>
            <Contributor_id>10000250/AS-Academia Sinica</Contributor_id>
            <Preferred>Non Preferred</Preferred>
          </Term_Contributor>
        </Term_Contributors>
        <Term_Sources>
          <Term_Source>
            <Source>
              <Source_ID>2000079740/AS-Academia Sinica data (2014-)</Source_ID>
            </Source>
            <Page>
            </Page>
            <Preferred>Non Preferred</Preferred>
          </Term_Source>
        </Term_Sources>
      </Non-Preferred_Term>
      <Non-Preferred_Term>
        <Term_Text>qiáng huà</Term_Text>
        <Display_Name>N/A</Display_Name>
        <Historic_Flag>Current</Historic_Flag>
        <Vernacular>Undetermined</Vernacular>
        <Term_ID>1000894502</Term_ID>
        <Term_Languages>
          <Term_Language>
            <Language>72584/Chinese (transliterated Hanyu Pinyin)</Language>
            <Preferred>Preferred</Preferred>
            <Qualifier>
            </Qualifier>
            <Term_Type>Used For Term</Term_Type>
            <Part_of_Speech>Undetermined</Part_of_Speech>
            <Lang_Stat>Undetermined</Lang_Stat>
          </Term_Language>
        </Term_Languages>
        <Term_Contributors>
          <Term_Contributor>
            <Contributor_id>10000250/AS-Academia Sinica</Contributor_id>
            <Preferred>Non Preferred</Preferred>
          </Term_Contributor>
        </Term_Contributors>
        <Term_Sources>
          <Term_Source>
            <Source>
              <Source_ID>2000079740/AS-Academia Sinica data (2014-)</Source_ID>
            </Source>
            <Page>
            </Page>
            <Preferred>Non Preferred</Preferred>
          </Term_Source>
        </Term_Sources>
      </Non-Preferred_Term>
    </Terms>
    <Subject_Contributors>
      <Subject_Contributor>
        <Contributor_id>10000000/VP</Contributor_id>
      </Subject_Contributor>
      <Subject_Contributor>
        <Contributor_id>10000205/AAT-Ned</Contributor_id>
      </Subject_Contributor>
      <Subject_Contributor>
        <Contributor_id>10000131/CDBP-SNPC</Contributor_id>
      </Subject_Contributor>
      <Subject_Contributor>
        <Contributor_id>10000250/AS-Academia Sinica</Contributor_id>
      </Subject_Contributor>
    </Subject_Contributors>
    <Subject_Sources>
      <Subject_Source>
        <Source>
          <Source_ID>2000094828/Getty Vocabulary Program rules</Source_ID>
        </Source>
      </Subject_Source>
      <Subject_Source>
        <Source>
          <Source_ID>2000000771/Adkins, Thesaurus of  British Archaeology (1982)</Source_ID>
        </Source>
      </Subject_Source>
      <Subject_Source>
        <Source>
          <Source_ID>2000001451/Grube, Architecture of the Islamic World (1978)</Source_ID>
        </Source>
      </Subject_Source>
      <Subject_Source>
        <Source>
          <Source_ID>2000046657/Avery Index (1963-)</Source_ID>
        </Source>
      </Subject_Source>
      <Subject_Source>
        <Source>
          <Source_ID>2000047206/BHA Subject Headings (1985-)</Source_ID>
        </Source>
      </Subject_Source>
      <Subject_Source>
        <Source>
          <Source_ID>2000048328/Contributed as a candidate term</Source_ID>
        </Source>
      </Subject_Source>
      <Subject_Source>
        <Source>
          <Source_ID>2000009281/Mumford, Culture of Cities (1938)</Source_ID>
        </Source>
      </Subject_Source>
      <Subject_Source>
        <Source>
          <Source_ID>2000012481/Down to Earth (1983)</Source_ID>
        </Source>
      </Subject_Source>
      <Subject_Source>
        <Source>
          <Source_ID>2000015171/Fletcher, History of Architecture (1975)</Source_ID>
        </Source>
      </Subject_Source>
      <Subject_Source>
        <Source>
          <Source_ID>2000017891/Guidoni, Primitive Architecture (1978)</Source_ID>
        </Source>
      </Subject_Source>
      <Subject_Source>
        <Source>
          <Source_ID>2000048487/Kostof, Castillo, and Tobias, History of Architecture (1995)</Source_ID>
        </Source>
      </Subject_Source>
      <Subject_Source>
        <Source>
          <Source_ID>2000034491/RCHME, Revised Thesaurus of Architectural Terms (1989)</Source_ID>
        </Source>
      </Subject_Source>
      <Subject_Source>
        <Source>
          <Source_ID>2000046682/Random House Dictionary of the English Language (1987)</Source_ID>
        </Source>
      </Subject_Source>
      <Subject_Source>
        <Source>
          <Source_ID>2000035111/RIBA, Architectural Keywords (1982)</Source_ID>
        </Source>
      </Subject_Source>
      <Subject_Source>
        <Source>
          <Source_ID>2000099099/Van Dale groot woordenboek (1994)</Source_ID>
        </Source>
      </Subject_Source>
    </Subject_Sources>
  </Subject>
</Vocabulary>